LICENSE
MANIFEST.in
README.md
setup.py
django_garage.egg-info/PKG-INFO
django_garage.egg-info/SOURCES.txt
django_garage.egg-info/dependency_links.txt
django_garage.egg-info/requires.txt
django_garage.egg-info/top_level.txt
docs/coming-soon.txt
garage/__init__.py
garage/cache.py
garage/datetime.py
garage/db.py
garage/exceptions.py
garage/help_text.py
garage/html_utils.py
garage/image_utils.py
garage/logger.py
garage/session.py
garage/slugify.py
garage/text_utils.py
garage/urlgen.py
garage/utils.py
garage/test/__init__.py
garage/test/base.py
garage/test/settings.py
garage/test/utils.py